seisbench/__init__.py
seisbench/util/arraytools.py
seisbench/util/region.py
seisbench/util/__init__.py
seisbench/util/file.py
seisbench/util/trace_ops.py
seisbench/util/torch_helpers.py
seisbench/util/annotations.py
seisbench/util/auxiliary.py
seisbench/util/decorators.py
seisbench/ext/utils.cpython-313-darwin.so
seisbench/ext/__init__.py
seisbench/ext/utils.pyi
seisbench/ext/utils.c
seisbench/models/eqtransformer.py
seisbench/models/dpp.py
seisbench/models/skynet.py
seisbench/models/__init__.py
seisbench/models/gpd.py
seisbench/models/team.py
seisbench/models/das_wrapper.py
seisbench/models/pickblue.py
seisbench/models/lfe_detect.py
seisbench/models/depthphase.py
seisbench/models/utils.py
seisbench/models/eqtp.py
seisbench/models/obstransformer.py
seisbench/models/aepicker.py
seisbench/models/deepdenoiser.py
seisbench/models/phasenet.py
seisbench/models/cred.py
seisbench/models/das_base.py
seisbench/models/base.py
seisbench/models/seisdae.py
seisbench/generate/augmentation.py
seisbench/generate/__init__.py
seisbench/generate/generator.py
seisbench/generate/windows.py
seisbench/generate/labeling.py
seisbench/data/bohemia.py
seisbench/data/instance.py
seisbench/data/pnw.py
seisbench/data/iquique.py
seisbench/data/ceed.py
seisbench/data/aq2009.py
seisbench/data/stead.py
seisbench/data/txed.py
seisbench/data/__init__.py
seisbench/data/geofon.py
seisbench/data/vcseis.py
seisbench/data/scedc.py
seisbench/data/inspection.py
seisbench/data/pisdl.py
seisbench/data/ethz.py
seisbench/data/lfe_stacks.py
seisbench/data/crew.py
seisbench/data/neic.py
seisbench/data/obs.py
seisbench/data/lendb.py
seisbench/data/dummy.py
seisbench/data/isc_ehb.py
seisbench/data/das_base.py
seisbench/data/base.py
seisbench/data/obst2024.py
seisbench/data/cwa.py
seisbench-0.11.0.dist-info/RECORD
seisbench-0.11.0.dist-info/WHEEL
seisbench-0.11.0.dist-info/top_level.txt
seisbench-0.11.0.dist-info/METADATA
seisbench-0.11.0.dist-info/licenses/LICENSE
