Metadata-Version: 2.4
Name: seisbench
Version: 0.11.0
Summary: The seismological machine learning benchmark collection
Author-email: Jack Woolam <jack.woollam@kit.edu>, Jannes Münchmeyer <munchmej@gfz-potsdam.de>
Maintainer-email: Jack Woolam <jack.woollam@kit.edu>, Jannes Münchmeyer <munchmej@gfz-potsdam.de>
License: GPLv3
Project-URL: GitHub, https://github.com/seisbench/seisbench
Project-URL: Documentation, https://seisbench.readthedocs.io/en/latest/
Project-URL: Issues, https://github.com/seisbench/seisbench/issues
Keywords: seismology,machine learning,signal processing,earthquake
Classifier: Intended Audience :: Science/Research
Classifier: Topic :: Scientific/Engineering
Classifier: Programming Language :: Python :: 3.9
Classifier: Operating System :: OS Independent
Classifier: License :: OSI Approved :: GNU General Public License v3 (GPLv3)
Requires-Python: >=3.10
License-File: LICENSE
Requires-Dist: numpy>=1.21.6
Requires-Dist: pandas>=1.1
Requires-Dist: h5py>=3.1
Requires-Dist: obspy>=1.3.1
Requires-Dist: tqdm>=4.52
Requires-Dist: torch>=1.10.0
Requires-Dist: scipy>=1.9
Requires-Dist: nest_asyncio>=1.5.3
Requires-Dist: bottleneck>=1.3
Requires-Dist: typing_extensions>=4.0
Provides-Extra: das
Requires-Dist: xdas>=0.2.3; extra == "das"
Requires-Dist: pyarrow; extra == "das"
Provides-Extra: dev
Requires-Dist: ruff; extra == "dev"
Requires-Dist: pre-commit; extra == "dev"
Provides-Extra: tests
Requires-Dist: pytest; extra == "tests"
Requires-Dist: pytest-asyncio>=0.26.0; extra == "tests"
Requires-Dist: pytest-benchmark; extra == "tests"
Dynamic: license-file
